{"id":"000390","is_deleted":false,"trip_update":{"trip":{"trip_id":"058550_6..S07X001","route_id":"6X","direction_id":null,"start_time":null,"start_date":"20170605","schedule_relationship":null},"vehicle":null,"stop_time_update":[{"stop_sequence":null,"stop_id":"607S","arrival":{"delay":null,"time":{"low":1496670928,"high":0,"unsigned":false},"uncertainty":null},"departure":{"delay":null,"time":{"low":1496670928,"high":0,"unsigned":false},"uncertainty":null},"schedule_relationship":0},{"stop_sequence":null,"stop_id":"608S","arrival":{"delay":null,"time":{"low":1496671048,"high":0,"unsigned":false},"uncertainty":null},"departure":{"delay":null,"time":{"low":1496671048,"high":0,"unsigned":false},"uncertainty":null},"schedule_relationship":0},{"stop_sequence":null,"stop_id":"609S","arrival":{"delay":null,"time":{"low":1496671138,"high":0,"unsigned":false},"uncertainty":null},"departure":{"delay":null,"time":{"low":1496671138,"high":0,"unsigned":false},"uncertainty":null},"schedule_relationship":0},{"stop_sequence":null,"stop_id":"610S","arrival":{"delay":null,"time":{"low":1496671228,"high":0,"unsigned":false},"uncertainty":null},"departure":{"delay":null,"time":{"low":1496671228,"high":0,"unsigned":false},"uncertainty":null},"schedule_relationship":0},{"stop_sequence":null,"stop_id":"611S","arrival":{"delay":null,"time":{"low":1496671288,"high":0,"unsigned":false},"uncertainty":null},"departure":{"delay":null,"time":{"low":1496671288,"high":0,"unsigned":false},"uncertainty":null},"schedule_relationship":0},{"stop_sequence":null,"stop_id":"612S","arrival":{"delay":null,"time":{"low":1496671408,"high":0,"unsigned":false},"uncertainty":null},"departure":{"delay":null,"time":{"low":1496671408,"high":0,"unsigned":false},"uncertainty":null},"schedule_relationship":0},{"stop_sequence":null,"stop_id":"613S","arrival":{"delay":null,"time":{"low":1496671528,"high":0,"unsigned":false},"uncertainty":null},"departure":{"delay":null,"time":{"low":1496671528,"high":0,"unsigned":false},"uncertainty":null},"schedule_relationship":0},{"stop_sequence":null,"stop_id":"619S","arrival":{"delay":null,"time":{"low":1496671948,"high":0,"unsigned":false},"uncertainty":null},"departure":{"delay":null,"time":{"low":1496671948,"high":0,"unsigned":false},"uncertainty":null},"schedule_relationship":0},{"stop_sequence":null,"stop_id":"621S","arrival":{"delay":null,"time":{"low":1496672128,"high":0,"unsigned":false},"uncertainty":null},"departure":{"delay":null,"time":{"low":1496672128,"high":0,"unsigned":false},"uncertainty":null},"schedule_relationship":0},{"stop_sequence":null,"stop_id":"622S","arrival":{"delay":null,"time":{"low":1496672218,"high":0,"unsigned":false},"uncertainty":null},"departure":{"delay":null,"time":{"low":1496672218,"high":0,"unsigned":false},"uncertainty":null},"schedule_relationship":0},{"stop_sequence":null,"stop_id":"623S","arrival":{"delay":null,"time":{"low":1496672308,"high":0,"unsigned":false},"uncertainty":null},"departure":{"delay":null,"time":{"low":1496672308,"high":0,"unsigned":false},"uncertainty":null},"schedule_relationship":0},{"stop_sequence":null,"stop_id":"624S","arrival":{"delay":null,"time":{"low":1496672368,"high":0,"unsigned":false},"uncertainty":null},"departure":{"delay":null,"time":{"low":1496672368,"high":0,"unsigned":false},"uncertainty":null},"schedule_relationship":0},{"stop_sequence":null,"stop_id":"625S","arrival":{"delay":null,"time":{"low":1496672458,"high":0,"unsigned":false},"uncertainty":null},"departure":{"delay":null,"time":{"low":1496672458,"high":0,"unsigned":false},"uncertainty":null},"schedule_relationship":0},{"stop_sequence":null,"stop_id":"626S","arrival":{"delay":null,"time":{"low":1496672578,"high":0,"unsigned":false},"uncertainty":null},"departure":{"delay":null,"time":{"low":1496672578,"high":0,"unsigned":false},"uncertainty":null},"schedule_relationship":0},{"stop_sequence":null,"stop_id":"627S","arrival":{"delay":null,"time":{"low":1496672698,"high":0,"unsigned":false},"uncertainty":null},"departure":{"delay":null,"time":{"low":1496672698,"high":0,"unsigned":false},"uncertainty":null},"schedule_relationship":0},{"stop_sequence":null,"stop_id":"628S","arrival":{"delay":null,"time":{"low":1496672818,"high":0,"unsigned":false},"uncertainty":null},"departure":{"delay":null,"time":{"low":1496672818,"high":0,"unsigned":false},"uncertainty":null},"schedule_relationship":0},{"stop_sequence":null,"stop_id":"629S","arrival":{"delay":null,"time":{"low":1496672908,"high":0,"unsigned":false},"uncertainty":null},"departure":{"delay":null,"time":{"low":1496672908,"high":0,"unsigned":false},"uncertainty":null},"schedule_relationship":0},{"stop_sequence":null,"stop_id":"630S","arrival":{"delay":null,"time":{"low":1496673028,"high":0,"unsigned":false},"uncertainty":null},"departure":{"delay":null,"time":{"low":1496673028,"high":0,"unsigned":false},"uncertainty":null},"schedule_relationship":0},{"stop_sequence":null,"stop_id":"631S","arrival":{"delay":null,"time":{"low":1496673148,"high":0,"unsigned":false},"uncertainty":null},"departure":{"delay":null,"time":{"low":1496673268,"high":0,"unsigned":false},"uncertainty":null},"schedule_relationship":0},{"stop_sequence":null,"stop_id":"632S","arrival":{"delay":null,"time":{"low":1496673388,"high":0,"unsigned":false},"uncertainty":null},"departure":{"delay":null,"time":{"low":1496673388,"high":0,"unsigned":false},"uncertainty":null},"schedule_relationship":0},{"stop_sequence":null,"stop_id":"633S","arrival":{"delay":null,"time":{"low":1496673448,"high":0,"unsigned":false},"uncertainty":null},"departure":{"delay":null,"time":{"low":1496673448,"high":0,"unsigned":false},"uncertainty":null},"schedule_relationship":0},{"stop_sequence":null,"stop_id":"634S","arrival":{"delay":null,"time":{"low":1496673508,"high":0,"unsigned":false},"uncertainty":null},"departure":{"delay":null,"time":{"low":1496673508,"high":0,"unsigned":false},"uncertainty":null},"schedule_relationship":0},{"stop_sequence":null,"stop_id":"635S","arrival":{"delay":null,"time":{"low":1496673598,"high":0,"unsigned":false},"uncertainty":null},"departure":{"delay":null,"time":{"low":1496673598,"high":0,"unsigned":false},"uncertainty":null},"schedule_relationship":0},{"stop_sequence":null,"stop_id":"636S","arrival":{"delay":null,"time":{"low":1496673688,"high":0,"unsigned":false},"uncertainty":null},"departure":{"delay":null,"time":{"low":1496673688,"high":0,"unsigned":false},"uncertainty":null},"schedule_relationship":0},{"stop_sequence":null,"stop_id":"637S","arrival":{"delay":null,"time":{"low":1496673778,"high":0,"unsigned":false},"uncertainty":null},"departure":{"delay":null,"time":{"low":1496673778,"high":0,"unsigned":false},"uncertainty":null},"schedule_relationship":0},{"stop_sequence":null,"stop_id":"638S","arrival":{"delay":null,"time":{"low":1496673838,"high":0,"unsigned":false},"uncertainty":null},"departure":{"delay":null,"time":{"low":1496673838,"high":0,"unsigned":false},"uncertainty":null},"schedule_relationship":0},{"stop_sequence":null,"stop_id":"639S","arrival":{"delay":null,"time":{"low":1496673928,"high":0,"unsigned":false},"uncertainty":null},"departure":{"delay":null,"time":{"low":1496674138,"high":0,"unsigned":false},"uncertainty":null},"schedule_relationship":0},{"stop_sequence":null,"stop_id":"640S","arrival":{"delay":null,"time":{"low":1496674258,"high":0,"unsigned":false},"uncertainty":null},"departure":null,"schedule_relationship":0}],"timestamp":null,"delay":null},"vehicle":null,"alert":null,"timestamp":1496670898}